Metadata-Version: 2.1
Name: bytesep
Version: 0.1.1
Summary: Music source separation
Home-page: https://github.com/bytedance/music_source_separation
Author: ByteDance
License: Apache 2.0
Platform: UNKNOWN
License-File: LICENSE
Requires-Dist: torch (==1.7.1)
Requires-Dist: librosa (==0.8.0)
Requires-Dist: museval (==0.4.0)
Requires-Dist: h5py (==2.10.0)
Requires-Dist: pytorch-lightning (==1.2.1)
Requires-Dist: numpy (==1.18.5)
Requires-Dist: torchlibrosa (==0.0.9)
Requires-Dist: matplotlib (==3.3.4)
Requires-Dist: musdb (==0.4.0)
Requires-Dist: samplerate (==0.1.0)
